pvoutput-0.1.0.dist-info/METADATA
pvoutput-0.1.0.dist-info/WHEEL
pvoutput-0.1.0.dist-info/entry_points.txt
pvoutput-0.1.0.dist-info/licenses/LICENSE
pvoutput/.DS_Store
pvoutput/__init__.py
pvoutput/asyncio/__init__.py
pvoutput/base.py
pvoutput/exceptions.py
pvoutput/parameters.py
pvoutput/py.typed
pvoutput/utils.py
pvoutput-0.1.0.dist-info/RECORD
