Metadata-Version: 2.1
Name: pvoutput
Version: 0.1.0
Summary: Interface to the PVOutput API
Author-Email: James Hodgkinson <james@terminaloutcomes.com>
License: MIT
Classifier: License :: OSI Approved :: MIT License
Classifier: Programming Language :: Python :: 3.10
Classifier: Programming Language :: Python :: 3.11
Classifier: Programming Language :: Python :: 3.12
Classifier: Programming Language :: Python :: 3.13
Classifier: Operating System :: OS Independent
Project-URL: homepage, https://yaleman.github.io/pvoutput/
Project-URL: repository, https://github.com/yaleman/pvoutput/
Requires-Python: >=3.10
Requires-Dist: requests>=2.27.1
Requires-Dist: aiohttp>=3.8.1
